Workbook
Name aporte: Principal!$D$8
Name patrimonio: Principal!$D$11
Name qtd_anos: Principal!$D$9
Name rendimento_carteira: Principal!$D$4
Name salario: Principal!$D$3
Name sugestao_invest: Principal!$D$5
Name taxa_mensal: Principal!$D$10

Sheet Principal
B2: CONFIGURAÇÕES
B3: Salário | D3: 2000
B4: Rendimento de carteira | D4: 0.6
B5: Sugestão de investimento | D5: =salario*30% -> 600
B7: INVESTIMENTO PESSOAL
B8: Quanto investir por mês? | D8: 200
B9: Por quantos anos? | D9: 5
B10: Taxa de rendimento mensal? | D10: 0.01079
B11: Patrimônio acumulado? | D11: =FV(taxa_mensal,qtd_anos*12,aporte*-1) -> 16755.383
B12: Dividendos mensais? | D12: =patrimonio*taxa_mensal -> 180.79058
B14: Cenários | D14: Dividendo
B15: Quanto em 2 anos | C15: =FV($D$10,2*12,$D$8*-1) -> 5445.5255 | D15: =C15*rendimento_carteira -> 3267.3153
B16: Quanto em 5 anos | C16: =FV($D$10,5*12,$D$8*-1) -> 16755.383 | D16: =C16*rendimento_carteira -> 10053.23
B17: Quanto em10 anos | C17: =FV($D$10,10*12,$D$8*-1) -> 48656.843 | D17: =C17*rendimento_carteira -> 29194.106
B18: Quanto em 20 anos | C18: =FV($D$10,20*12,$D$8*-1) -> 225039.68 | D18: =C18*rendimento_carteira -> 135023.81
B19: Quanto em 30 anos | C19: =FV($D$10,30*12,$D$8*-1) -> 864433.93 | D19: =C19*rendimento_carteira -> 518660.36
B21: PERFIL | C21: Conservador
B22: Valor a ser investido mensalmente | C22: =aporte -> 200
B24: TIPO DE FII | C24: Percentual sugerido | D24: Valores
B25: PAPEL | C25: =VLOOKUP($C$21&"-"&B25,Apoio!$A:$D,4,FALSE) -> 0.3 | D25: =C22*C25 -> 60
B26: TIJOLO | C26: =VLOOKUP($C$21&"-"&B26,Apoio!$A:$D,4,FALSE) -> 0.5 | D26: =C22*C26 -> 100
B27: HIBRIDOS | C27: =VLOOKUP($C$21&"-"&B27,Apoio!$A:$D,4,FALSE) -> 0.1 | D27: =C22*C27 -> 20
B28: FOFIS | C28: =VLOOKUP($C$21&"-"&B28,Apoio!$A:$D,4,FALSE) -> 0.1 | D28: =C22*C28 -> 20
B29: DESENVOLVIMENTO | C29: =VLOOKUP($C$21&"-"&B29,Apoio!$A:$D,4,FALSE) -> 0 | D29: =C22*C29 -> 0
B30: HOTELARIAS | C30: =VLOOKUP($C$21&"-"&B30,Apoio!$A:$D,4,FALSE) -> 0 | D30: =C22*C30 -> 0
D31: =SUM(D25:D30) -> 200

Sheet Apoio
A2: CHAVE | B2: PERFIL | C2: TIPO DE FII | D2: % | H2: %
A3: =$B$3&"-"&C3 -> CONSERVADOR-PAPEL | B3: CONSERVADOR | C3: PAPEL | D3: 0.3 | G3: MODERADO-TIJOLO | H3: =VLOOKUP(A10,$A:$D,2,FALSE) -> MODERADO
A4: =$B$3&"-"&C4 -> CONSERVADOR-TIJOLO | B4: CONSERVADOR | C4: TIJOLO | D4: 0.5
A5: =$B$3&"-"&C5 -> CONSERVADOR-HIBRIDOS | B5: CONSERVADOR | C5: HIBRIDOS | D5: 0.1
A6: =$B$3&"-"&C6 -> CONSERVADOR-FOFIS | B6: CONSERVADOR | C6: FOFIS | D6: 0.1
A7: =$B$3&"-"&C7 -> CONSERVADOR-DESENVOLVIMENTO | B7: CONSERVADOR | C7: DESENVOLVIMENTO | D7: 0
A8: =$B$3&"-"&C8 -> CONSERVADOR-HOTELARIAS | B8: CONSERVADOR | C8: HOTELARIAS | D8: 0
A9: =$B$9&"-"&C9 -> MODERADO-PAPEL | B9: MODERADO | C9: PAPEL | D9: 0.32
A10: =$B$9&"-"&C10 -> MODERADO-TIJOLO | B10: MODERADO | C10: TIJOLO | D10: 0.35
A11: =$B$9&"-"&C11 -> MODERADO-HIBRIDOS | B11: MODERADO | C11: HIBRIDOS | D11: 0.08
A12: =$B$9&"-"&C12 -> MODERADO-FOFIS | B12: MODERADO | C12: FOFIS | D12: 0.05
A13: =$B$9&"-"&C13 -> MODERADO-DESENVOLVIMENTO | B13: MODERADO | C13: DESENVOLVIMENTO | D13: 0.1
A14: =$B$9&"-"&C14 -> MODERADO-HOTELARIAS | B14: MODERADO | C14: HOTELARIAS | D14: 0.1
A15: =$B$15&"-"&C15 -> AGRESSIVO-PAPEL | B15: AGRESSIVO | C15: PAPEL | D15: 0.5
A16: =$B$15&"-"&C16 -> AGRESSIVO-TIJOLO | B16: AGRESSIVO | C16: TIJOLO | D16: 0.1
A17: =$B$15&"-"&C17 -> AGRESSIVO-HIBRIDOS | B17: AGRESSIVO | C17: HIBRIDOS | D17: 0.05
A18: =$B$15&"-"&C18 -> AGRESSIVO-FOFIS | B18: AGRESSIVO | C18: FOFIS | D18: 0.05
A19: =$B$15&"-"&C19 -> AGRESSIVO-DESENVOLVIMENTO | B19: AGRESSIVO | C19: DESENVOLVIMENTO | D19: 0.2
A20: =$B$15&"-"&C20 -> AGRESSIVO-HOTELARIAS | B20: AGRESSIVO | C20: HOTELARIAS | D20: 0.1
